finja/__init__.py
finja/version.py
finja-1.1.1.dist-info/LICENSE
finja-1.1.1.dist-info/METADATA
finja-1.1.1.dist-info/WHEEL
finja-1.1.1.dist-info/entry_points.txt
finja-1.1.1.dist-info/top_level.txt
finja-1.1.1.dist-info/RECORD
