Metadata-Version: 2.1
Name: finja
Version: 1.1.1
Summary: Index stuff and find it fast and without bloat
Home-page: https://www.adfinis-sygroup.ch
Author: Jean-Louis Fuchs, David Vogt, Stefan Heinemann, Pablo Vergés
Author-email: ganwell@fangorn.ch
License: UNKNOWN
Keywords: code index find text open
Platform: UNKNOWN
Classifier: Development Status :: 5 - Production/Stable
Classifier: Environment :: Console
Classifier: Intended Audience :: Developers
Classifier: Intended Audience :: Information Technology
Classifier: License :: OSI Approved :: GNU Affero General Public License v3
Classifier: Natural Language :: English
Classifier: Operating System :: OS Independent
Classifier: Programming Language :: Python :: 2.6
Classifier: Programming Language :: Python :: 2.7
Classifier: Programming Language :: Python :: 3.5
Classifier: Programming Language :: Python :: 3.7
Classifier: Programming Language :: Python :: Implementation :: PyPy
Requires-Dist: binaryornot
Requires-Dist: six
Requires-Dist: chardet
Requires-Dist: termcolor
